jobpilot_integrations/__init__.py
jobpilot_integrations/contracts.py
jobpilot_integrations/main.py
jobpilot_integrations/integrations/__init__.py
jobpilot_integrations/integrations/dice.py
jobpilot_integrations/integrations/djinni.py
jobpilot_integrations/integrations/indeed.py
jobpilot_integrations/integrations/remoteok.py
jobpilot_integrations-0.1.3.dist-info/METADATA
jobpilot_integrations-0.1.3.dist-info/WHEEL
jobpilot_integrations-0.1.3.dist-info/top_level.txt
jobpilot_integrations-0.1.3.dist-info/RECORD
