Metadata-Version: 2.4
Name: jobpilot-integrations
Version: 0.1.3
Summary: Add your description here
Requires-Python: >=3.13
Requires-Dist: beautifulsoup4>=4.13.4
Requires-Dist: httpx>=0.28.1
